{
  "app-id": "com.example.QuickView",
  "runtime": "org.gnome.Platform",
  "runtime-version": "49",
  "sdk": "org.gnome.Sdk",
  "command": "quickview",
  "finish-args": [
    "--share=ipc",
    "--socket=wayland",
    "--filesystem=host:ro"
  ],
  "modules": [
    {
      "name": "quickview",
      "buildsystem": "simple",
      "build-commands": [
        "cargo build --release --locked",
        "install -Dm755 target/release/quickview /app/bin/quickview",
        "install -Dm644 assets/desktop/com.example.QuickView.desktop /app/share/applications/com.example.QuickView.desktop",
        "install -Dm644 assets/metainfo/com.example.QuickView.metainfo.xml /app/share/metainfo/com.example.QuickView.metainfo.xml",
        "install -Dm644 assets/icons/hicolor/scalable/apps/com.example.QuickView.svg /app/share/icons/hicolor/scalable/apps/com.example.QuickView.svg",
        "install -Dm644 LICENSE /app/share/licenses/quickview/LICENSE"
      ],
      "sources": [
        { "type": "dir", "path": "../../" }
      ]
    }
  ]
}
